{
  "project_info": {
    "project_number": "1098404694826",
    "firebase_url": "https://alert247.firebaseio.com",
    "project_id": "alert247",
    "storage_bucket": "alert247.appspot.com"
  },
  "client": [
    {
      "client_info": {
        "mobilesdk_app_id": "1:1098404694826:android:087c9f950028b57e",
        "android_client_info": {
          "package_name": "gr.avmap.alert247"
        }
      },
      "oauth_client": [
        {
          "client_id": "1098404694826-cn3876qcm1571aok58vruo3mkplkdqnb.apps.googleusercontent.com",
          "client_type": 3
        }
      ],
      "api_key": [
        {
          "current_key": "AIzaSyD__1He2oD8ujyJkOaVex3lRc9YjzieMUU"
        }
      ],
      "services": {
        "appinvite_service": {
          "other_platform_oauth_client": [
            {
              "client_id": "1098404694826-cn3876qcm1571aok58vruo3mkplkdqnb.apps.googleusercontent.com",
              "client_type": 3
            }
          ]
        }
      }
    }
  ],
  "configuration_version": "1"
}